maleo/research/__init__.py
maleo/research/imaging/__init__.py
maleo/research/imaging/dtos.py
maleo/research/imaging/constants/__init__.py
maleo/research/imaging/constants/annotation.py
maleo/research/imaging/constants/common.py
maleo/research/imaging/enums/__init__.py
maleo/research/imaging/enums/annotation.py
maleo/research/imaging/mixins/__init__.py
maleo/research/imaging/mixins/annotation.py
maleo/research/imaging/mixins/diagnosis.py
maleo/research/imaging/schemas/__init__.py
maleo/research/imaging/schemas/annotation.py
maleo/research/imaging/schemas/common.py
maleo/research/imaging/types/__init__.py
maleo/research/imaging/types/annotation.py
maleo_research-0.0.10.dist-info/licenses/LICENSE
maleo_research-0.0.10.dist-info/METADATA
maleo_research-0.0.10.dist-info/WHEEL
maleo_research-0.0.10.dist-info/top_level.txt
maleo_research-0.0.10.dist-info/RECORD
