Metadata-Version: 2.4
Name: maleo-research
Version: 0.0.10
Summary: MaleoResearch service package
Author-email: Agra Bima Yuda <agra@nexmedis.com>
License: Proprietary
Requires-Python: >=3.12
License-File: LICENSE
Requires-Dist: annotated-doc>=0.0.4
Requires-Dist: annotated-types>=0.7.0
Requires-Dist: anyio>=4.12.1
Requires-Dist: bcrypt>=5.0.0
Requires-Dist: black>=25.12.0
Requires-Dist: cachetools>=6.2.4
Requires-Dist: certifi>=2026.1.4
Requires-Dist: cffi>=2.0.0
Requires-Dist: cfgv>=3.5.0
Requires-Dist: charset-normalizer>=3.4.4
Requires-Dist: click>=8.3.1
Requires-Dist: colorama>=0.4.6
Requires-Dist: cryptography>=46.0.3
Requires-Dist: distlib>=0.4.0
Requires-Dist: fastapi>=0.128.0
Requires-Dist: filelock>=3.20.2
Requires-Dist: google-api-core>=2.28.1
Requires-Dist: google-auth>=2.47.0
Requires-Dist: google-cloud-appengine-logging>=1.7.0
Requires-Dist: google-cloud-audit-log>=0.4.0
Requires-Dist: google-cloud-core>=2.5.0
Requires-Dist: google-cloud-logging>=3.13.0
Requires-Dist: google-cloud-pubsub>=2.34.0
Requires-Dist: googleapis-common-protos>=1.72.0
Requires-Dist: greenlet>=3.3.0
Requires-Dist: grpc-google-iam-v1>=0.14.3
Requires-Dist: grpcio>=1.76.0
Requires-Dist: grpcio-status>=1.76.0
Requires-Dist: h11>=0.16.0
Requires-Dist: httpcore>=1.0.9
Requires-Dist: httpx>=0.28.1
Requires-Dist: identify>=2.6.15
Requires-Dist: idna>=3.11
Requires-Dist: importlib_metadata>=8.7.1
Requires-Dist: iniconfig>=2.3.0
Requires-Dist: mypy_extensions>=1.1.0
Requires-Dist: nexo-crypto>=0.0.5
Requires-Dist: nexo-enums>=0.0.5
Requires-Dist: nexo-logging>=0.0.5
Requires-Dist: nexo-schemas>=0.0.19
Requires-Dist: nexo-types>=0.0.5
Requires-Dist: nexo-utils>=0.0.5
Requires-Dist: nodeenv>=1.10.0
Requires-Dist: opentelemetry-api>=1.39.1
Requires-Dist: opentelemetry-sdk>=1.39.1
Requires-Dist: opentelemetry-semantic-conventions>=0.60b1
Requires-Dist: packaging>=25.0
Requires-Dist: pathspec>=1.0.1
Requires-Dist: platformdirs>=4.5.1
Requires-Dist: pluggy>=1.6.0
Requires-Dist: pre_commit>=4.5.1
Requires-Dist: proto-plus>=1.27.0
Requires-Dist: protobuf>=6.33.2
Requires-Dist: pyasn1>=0.6.1
Requires-Dist: pyasn1_modules>=0.4.2
Requires-Dist: pycparser>=2.23
Requires-Dist: pycryptodome>=3.23.0
Requires-Dist: pydantic>=2.12.5
Requires-Dist: pydantic-settings>=2.12.0
Requires-Dist: pydantic_core>=2.41.5
Requires-Dist: Pygments>=2.19.2
Requires-Dist: PyJWT>=2.10.1
Requires-Dist: pytest>=9.0.2
Requires-Dist: python-dotenv>=1.2.1
Requires-Dist: pytokens>=0.3.0
Requires-Dist: PyYAML>=6.0.3
Requires-Dist: requests>=2.32.5
Requires-Dist: rsa>=4.9.1
Requires-Dist: sniffio>=1.3.1
Requires-Dist: SQLAlchemy>=2.0.45
Requires-Dist: starlette>=0.50.0
Requires-Dist: typing-inspection>=0.4.2
Requires-Dist: typing_extensions>=4.15.0
Requires-Dist: ua-parser>=1.0.1
Requires-Dist: ua-parser-builtins>=202601
Requires-Dist: urllib3>=2.6.3
Requires-Dist: user-agents>=2.2.0
Requires-Dist: virtualenv>=20.36.0
Requires-Dist: zipp>=3.23.0
Dynamic: license-file
